ConfigLoader/__init__.py
ConfigLoader/config_reader.py
ExperimentTracking/__init__.py
ExperimentTracking/tracker.py
ExperimentTracking/training_tracker.py
utils/__init__.py
utils/logger.py
mlflowsdk-0.1.0.dist-info/METADATA
mlflowsdk-0.1.0.dist-info/WHEEL
mlflowsdk-0.1.0.dist-info/top_level.txt
mlflowsdk-0.1.0.dist-info/RECORD
