Metadata-Version: 2.4
Name: mlflowsdk
Version: 0.1.0
Summary: cybage mlflow sdk
Author: AI Cloud Data Team - [Viraj]
License: MIT
Requires-Dist: PyYAML==6.0.2
Requires-Dist: mlflow==2.22.0
Requires-Dist: tensorflow==2.19.0
Requires-Dist: lightgbm==4.6.0
Requires-Dist: xgboost==3.0.2
Dynamic: author
Dynamic: license
Dynamic: requires-dist
Dynamic: summary
